{
    "leagues": [
        {
            "ccode": "ISL",
            "id": 216,
            "primaryId": 216,
            "name": "1. Deild",
            "matches": [
                {
                    "id": 5225774,
                    "leagueId": 216,
                    "time": "01.06.2026 21:15",
                    "home": {
                        "id": 4661,
                        "score": 0,
                        "name": "Throttur Reykjavik",
                        "longName": "Throttur Reykjavik"
                    },
                    "away": {
                        "id": 8298,
                        "score": 0,
                        "name": "Grindavik",
                        "longName": "Grindavik"
                    },
                    "eliminatedTeamId": null,
                    "statusId": 1,
                    "tournamentStage": "7",
                    "status": {
                        "utcTime": "2026-06-01T19:15:00.000Z",
                        "halfs": {
                            "firstHalfStarted": "01.06.2026 21:15:00"
                        },
                        "periodLength": 45,
                        "started": false,
                        "cancelled": false,
                        "finished": false
                    },
                    "timeTS": 1780341300000
                }
            ],
            "internalRank": 99,
            "liveRank": 999,
            "simpleLeague": false
        },
        {
            "ccode": "ISL",
            "id": 10226,
            "primaryId": 10226,
            "name": "2. Deild",
            "matches": [
                {
                    "id": 5225894,
                    "leagueId": 10226,
                    "time": "01.06.2026 21:15",
                    "home": {
                        "id": 542586,
                        "score": 0,
                        "name": "KFG",
                        "longName": "KFG"
                    },
                    "away": {
                        "id": 4518,
                        "score": 0,
                        "name": "Fj\u00f6lnir",
                        "longName": "Fj\u00f6lnir"
                    },
                    "eliminatedTeamId": null,
                    "statusId": 1,
                    "tournamentStage": "5",
                    "status": {
                        "utcTime": "2026-06-01T19:15:00.000Z",
                        "halfs": {
                            "firstHalfStarted": "01.06.2026 21:15:00"
                        },
                        "periodLength": 45,
                        "started": false,
                        "cancelled": false,
                        "finished": false
                    },
                    "timeTS": 1780341300000
                }
            ],
            "internalRank": 0,
            "liveRank": 999,
            "simpleLeague": false
        },
        {
            "isGroup": true,
            "groupName": "3",
            "ccode": "NOR",
            "id": 919794,
            "primaryId": 205,
            "name": "3. Divisjon Avd. 3",
            "matches": [
                {
                    "id": 5144130,
                    "leagueId": 919794,
                    "time": "01.06.2026 18:00",
                    "home": {
                        "id": 8469,
                        "score": 0,
                        "name": "Brann 2",
                        "longName": "Brann 2"
                    },
                    "away": {
                        "id": 8291,
                        "score": 0,
                        "name": "Ask\u00f8y",
                        "longName": "Ask\u00f8y"
                    },
                    "eliminatedTeamId": null,
                    "statusId": 1,
                    "tournamentStage": "9",
                    "status": {
                        "utcTime": "2026-06-01T16:00:00.000Z",
                        "halfs": {
                            "firstHalfStarted": "01.06.2026 18:00:00"
                        },
                        "periodLength": 45,
                        "started": false,
                        "cancelled": false,
                        "finished": false
                    },
                    "timeTS": 1780329600000
                },
                {
                    "id": 5144129,
                    "leagueId": 919794,
                    "time": "01.06.2026 18:00",
                    "home": {
                        "id": 8117,
                        "score": 0,
                        "name": "Vard Haugesund",
                        "longName": "Vard Haugesund"
                    },
                    "away": {
                        "id": 246204,
                        "score": 0,
                        "name": "\u00c5sane 2",
                        "longName": "\u00c5sane 2"
                    },
                    "eliminatedTeamId": null,
                    "statusId": 1,
                    "tournamentStage": "9",
                    "status": {
                        "utcTime": "2026-06-01T16:00:00.000Z",
                        "halfs": {
                            "firstHalfStarted": "01.06.2026 18:00:00"
                        },
                        "periodLength": 45,
                        "started": false,
                        "cancelled": false,
                        "finished": false
                    },
                    "timeTS": 1780329600000
                },
                {
                    "id": 5144131,
                    "leagueId": 919794,
                    "time": "01.06.2026 18:30",
                    "home": {
                        "id": 4305,
                        "score": 0,
                        "name": "Gneist",
                        "longName": "Gneist"
                    },
                    "away": {
                        "id": 4384,
                        "score": 0,
                        "name": "Sogndal 2",
                        "longName": "Sogndal 2"
                    },
                    "eliminatedTeamId": null,
                    "statusId": 1,
                    "tournamentStage": "9",
                    "status": {
                        "utcTime": "2026-06-01T16:30:00.000Z",
                        "halfs": {
                            "firstHalfStarted": "01.06.2026 18:30:00"
                        },
                        "periodLength": 45,
                        "started": false,
                        "cancelled": false,
                        "finished": false
                    },
                    "timeTS": 1780331400000
                }
            ],
            "parentLeagueId": 205,
            "parentLeagueName": "Norsk Tipping-ligaen",
            "internalRank": 0,
            "liveRank": 999,
            "simpleLeague": false
        },
        {
            "isGroup": true,
            "groupName": "6",
            "ccode": "NOR",
            "id": 919797,
            "primaryId": 205,
            "name": "3. Divisjon Avd. 6",
            "matches": [
                {
                    "id": 5144688,
                    "leagueId": 919797,
                    "time": "01.06.2026 20:00",
                    "home": {
                        "id": 4244,
                        "score": 0,
                        "name": "Lyn 2",
                        "longName": "Lyn 2"
                    },
                    "away": {
                        "id": 8183,
                        "score": 0,
                        "name": "Gj\u00f8vik-Lyn",
                        "longName": "Gj\u00f8vik-Lyn"
                    },
                    "eliminatedTeamId": null,
                    "statusId": 1,
                    "tournamentStage": "9",
                    "status": {
                        "utcTime": "2026-06-01T18:00:00.000Z",
                        "halfs": {
                            "firstHalfStarted": "01.06.2026 20:00:00"
                        },
                        "periodLength": 45,
                        "started": false,
                        "cancelled": false,
                        "finished": false
                    },
                    "timeTS": 1780336800000
                }
            ],
            "parentLeagueId": 205,
            "parentLeagueName": "Norsk Tipping-ligaen",
            "internalRank": 0,
            "liveRank": 999,
            "simpleLeague": false
        },
        {
            "ccode": "IRN",
            "id": 9372,
            "primaryId": 9372,
            "name": "Azadegan League",
            "matches": [
                {
                    "id": 5180969,
                    "leagueId": 9372,
                    "time": "02.06.2026 15:00",
                    "home": {
                        "id": 1528916,
                        "score": 0,
                        "name": "Kara Gostar",
                        "longName": "Kara Gostar"
                    },
                    "away": {
                        "id": 396142,
                        "score": 0,
                        "name": "Niroye Zamini",
                        "longName": "Niroye Zamini"
                    },
                    "eliminatedTeamId": null,
                    "statusId": 1,
                    "tournamentStage": "27",
                    "status": {
                        "utcTime": "2026-06-02T13:00:00.000Z",
                        "halfs": {
                            "firstHalfStarted": "02.06.2026 15:00:00"
                        },
                        "periodLength": 45,
                        "started": false,
                        "cancelled": false,
                        "finished": false
                    },
                    "timeTS": 1780405200000
                },
                {
                    "id": 5180971,
                    "leagueId": 9372,
                    "time": "02.06.2026 15:30",
                    "home": {
                        "id": 1693132,
                        "score": 0,
                        "name": "FC Fard",
                        "longName": "FC Fard"
                    },
                    "away": {
                        "id": 101622,
                        "score": 0,
                        "name": "Mes Kerman",
                        "longName": "Mes Kerman"
                    },
                    "eliminatedTeamId": null,
                    "statusId": 1,
                    "tournamentStage": "27",
                    "status": {
                        "utcTime": "2026-06-02T13:30:00.000Z",
                        "halfs": {
                            "firstHalfStarted": "02.06.2026 15:30:00"
                        },
                        "periodLength": 45,
                        "started": false,
                        "cancelled": false,
                        "finished": false
                    },
                    "timeTS": 1780407000000
                },
                {
                    "id": 5180972,
                    "leagueId": 9372,
                    "time": "02.06.2026 15:30",
                    "home": {
                        "id": 955322,
                        "score": 0,
                        "name": "Havadar SC",
                        "longName": "Havadar SC"
                    },
                    "away": {
                        "id": 958608,
                        "score": 0,
                        "name": "Navad",
                        "longName": "Navad Urmia"
                    },
                    "eliminatedTeamId": null,
                    "statusId": 1,
                    "tournamentStage": "27",
                    "status": {
                        "utcTime": "2026-06-02T13:30:00.000Z",
                        "halfs": {
                            "firstHalfStarted": "02.06.2026 15:30:00"
                        },
                        "periodLength": 45,
                        "started": false,
                        "cancelled": false,
                        "finished": false
                    },
                    "timeTS": 1780407000000
                },
                {
                    "id": 5180974,
                    "leagueId": 9372,
                    "time": "02.06.2026 15:30",
                    "home": {
                        "id": 961464,
                        "score": 0,
                        "name": "Mes Shahr Babak",
                        "longName": "Mes Shahr Babak"
                    },
                    "away": {
                        "id": 101624,
                        "score": 0,
                        "name": "Sanat-Naft",
                        "longName": "Sanat Naft Abadan"
                    },
                    "eliminatedTeamId": null,
                    "statusId": 1,
                    "tournamentStage": "27",
                    "status": {
                        "utcTime": "2026-06-02T13:30:00.000Z",
                        "halfs": {
                            "firstHalfStarted": "02.06.2026 15:30:00"
                        },
                        "periodLength": 45,
                        "started": false,
                        "cancelled": false,
                        "finished": false
                    },
                    "timeTS": 1780407000000
                },
                {
                    "id": 5180975,
                    "leagueId": 9372,
                    "time": "02.06.2026 15:30",
                    "home": {
                        "id": 392200,
                        "score": 0,
                        "name": "Nassaji",
                        "longName": "Nassaji Mazandaran FC"
                    },
                    "away": {
                        "id": 101627,
                        "score": 0,
                        "name": "Damash",
                        "longName": "Damash"
                    },
                    "eliminatedTeamId": null,
                    "statusId": 1,
                    "tournamentStage": "27",
                    "status": {
                        "utcTime": "2026-06-02T13:30:00.000Z",
                        "halfs": {
                            "firstHalfStarted": "02.06.2026 15:30:00"
                        },
                        "periodLength": 45,
                        "started": false,
                        "cancelled": false,
                        "finished": false
                    },
                    "timeTS": 1780407000000
                },
                {
                    "id": 5180970,
                    "leagueId": 9372,
                    "time": "02.06.2026 16:00",
                    "home": {
                        "id": 1431260,
                        "score": 0,
                        "name": "Ario Islamshahr",
                        "longName": "Ario Islamshahr"
                    },
                    "away": {
                        "id": 1320146,
                        "score": 0,
                        "name": "Shahrdari Nowshahr",
                        "longName": "Shahrdari Nowshahr"
                    },
                    "eliminatedTeamId": null,
                    "statusId": 1,
                    "tournamentStage": "27",
                    "status": {
                        "utcTime": "2026-06-02T14:00:00.000Z",
                        "halfs": {
                            "firstHalfStarted": "02.06.2026 16:00:00"
                        },
                        "periodLength": 45,
                        "started": false,
                        "cancelled": false,
                        "finished": false
                    },
                    "timeTS": 1780408800000
                },
                {
                    "id": 5180977,
                    "leagueId": 9372,
                    "time": "02.06.2026 16:30",
                    "home": {
                        "id": 1602400,
                        "score": 0,
                        "name": "Shenavarsazi Qeshm",
                        "longName": "Shenavarsazi Qeshm"
                    },
                    "away": {
                        "id": 101615,
                        "score": 0,
                        "name": "Saipa",
                        "longName": "Saipa"
                    },
                    "eliminatedTeamId": null,
                    "statusId": 1,
                    "tournamentStage": "27",
                    "status": {
                        "utcTime": "2026-06-02T14:30:00.000Z",
                        "halfs": {
                            "firstHalfStarted": "02.06.2026 16:30:00"
                        },
                        "periodLength": 45,
                        "started": false,
                        "cancelled": false,
                        "finished": false
                    },
                    "timeTS": 1780410600000
                },
                {
                    "id": 5180976,
                    "leagueId": 9372,
                    "time": "02.06.2026 16:45",
                    "home": {
                        "id": 775750,
                        "score": 0,
                        "name": "Pars Jonoubi",
                        "longName": "Pars Jonoubi Jam"
                    },
                    "away": {
                        "id": 1675873,
                        "score": 0,
                        "name": "Naft Bandar Abbas",
                        "longName": "Naft Bandar Abbas"
                    },
                    "eliminatedTeamId": null,
                    "statusId": 1,
                    "tournamentStage": "27",
                    "status": {
                        "utcTime": "2026-06-02T14:45:00.000Z",
                        "halfs": {
                            "firstHalfStarted": "02.06.2026 16:45:00"
                        },
                        "periodLength": 45,
                        "started": false,
                        "cancelled": false,
                        "finished": false
                    },
                    "timeTS": 1780411500000
                }
            ],
            "internalRank": 8,
            "liveRank": 999,
            "simpleLeague": false
        },
        {
            "ccode": "MAR",
            "id": 530,
            "primaryId": 530,
            "name": "Botola Pro",
            "matches": [
                {
                    "id": 5658893,
                    "leagueId": 530,
                    "time": "01.06.2026 18:00",
                    "home": {
                        "id": 320835,
                        "score": 0,
                        "name": "Union Touarga Sport",
                        "longName": "Union Touarga Sport"
                    },
                    "away": {
                        "id": 102042,
                        "score": 0,
                        "name": "KACM",
                        "longName": "KACM"
                    },
                    "eliminatedTeamId": null,
                    "statusId": 1,
                    "tournamentStage": "22",
                    "status": {
                        "utcTime": "2026-06-01T16:00:00.000Z",
                        "halfs": {
                            "firstHalfStarted": "01.06.2026 18:00:00"
                        },
                        "periodLength": 45,
                        "started": false,
                        "cancelled": false,
                        "finished": false
                    },
                    "timeTS": 1780329600000
                },
                {
                    "id": 5658894,
                    "leagueId": 530,
                    "time": "01.06.2026 20:00",
                    "home": {
                        "id": 102047,
                        "score": 0,
                        "name": "Olympic Club de Safi",
                        "longName": "Olympic Club de Safi"
                    },
                    "away": {
                        "id": 102043,
                        "score": 0,
                        "name": "MAS Fes",
                        "longName": "MAS Fes"
                    },
                    "eliminatedTeamId": null,
                    "statusId": 1,
                    "tournamentStage": "22",
                    "status": {
                        "utcTime": "2026-06-01T18:00:00.000Z",
                        "halfs": {
                            "firstHalfStarted": "01.06.2026 20:00:00"
                        },
                        "periodLength": 45,
                        "started": false,
                        "cancelled": false,
                        "finished": false
                    },
                    "timeTS": 1780336800000
                },
                {
                    "id": 5658895,
                    "leagueId": 530,
                    "time": "01.06.2026 22:00",
                    "home": {
                        "id": 102032,
                        "score": 0,
                        "name": "CODM Meknes",
                        "longName": "CODM Meknes"
                    },
                    "away": {
                        "id": 570487,
                        "score": 0,
                        "name": "Olympique Dcheira",
                        "longName": "Olympique Dcheira"
                    },
                    "eliminatedTeamId": null,
                    "statusId": 1,
                    "tournamentStage": "22",
                    "status": {
                        "utcTime": "2026-06-01T20:00:00.000Z",
                        "halfs": {
                            "firstHalfStarted": "01.06.2026 22:00:00"
                        },
                        "periodLength": 45,
                        "started": false,
                        "cancelled": false,
                        "finished": false
                    },
                    "timeTS": 1780344000000
                }
            ],
            "internalRank": 0,
            "liveRank": 999,
            "simpleLeague": false
        },
        {
            "ccode": "SWE",
            "id": 918043,
            "primaryId": 169,
            "name": "Ettan Norra",
            "matches": [
                {
                    "id": 5127485,
                    "leagueId": 918043,
                    "time": "01.06.2026 19:30",
                    "home": {
                        "id": 841094,
                        "score": 0,
                        "name": "FC Arlanda",
                        "longName": "FC Arlanda"
                    },
                    "away": {
                        "id": 7997,
                        "score": 0,
                        "name": "Gefle",
                        "longName": "Gefle"
                    },
                    "eliminatedTeamId": null,
                    "statusId": 1,
                    "tournamentStage": "10",
                    "status": {
                        "utcTime": "2026-06-01T17:30:00.000Z",
                        "halfs": {
                            "firstHalfStarted": "01.06.2026 19:30:00"
                        },
                        "periodLength": 45,
                        "started": false,
                        "cancelled": false,
                        "finished": false
                    },
                    "timeTS": 1780335000000
                }
            ],
            "parentLeagueId": 169,
            "internalRank": 0,
            "liveRank": 999,
            "simpleLeague": false
        },
        {
            "ccode": "SWE",
            "id": 918053,
            "primaryId": 169,
            "name": "Ettan Soedra",
            "matches": [
                {
                    "id": 5127838,
                    "leagueId": 918053,
                    "time": "01.06.2026 19:00",
                    "home": {
                        "id": 6153,
                        "score": 0,
                        "name": "Sk\u00f6vde AIK",
                        "longName": "Sk\u00f6vde AIK"
                    },
                    "away": {
                        "id": 8510,
                        "score": 0,
                        "name": "J\u00f6nk\u00f6ping S.",
                        "longName": "J\u00f6nk\u00f6ping S."
                    },
                    "eliminatedTeamId": null,
                    "statusId": 1,
                    "tournamentStage": "10",
                    "status": {
                        "utcTime": "2026-06-01T17:00:00.000Z",
                        "halfs": {
                            "firstHalfStarted": "01.06.2026 19:00:00"
                        },
                        "periodLength": 45,
                        "started": false,
                        "cancelled": false,
                        "finished": false
                    },
                    "timeTS": 1780333200000
                }
            ],
            "parentLeagueId": 169,
            "internalRank": 0,
            "liveRank": 999,
            "simpleLeague": false
        },
        {
            "ccode": "INT",
            "id": 914609,
            "primaryId": 114,
            "name": "Friendlies",
            "matches": [
                {
                    "id": 5343851,
                    "leagueId": 914609,
                    "time": "01.06.2026 18:00",
                    "home": {
                        "id": 10150,
                        "score": 0,
                        "name": "Bulgaria",
                        "longName": "Bulgaria"
                    },
                    "away": {
                        "id": 49437,
                        "score": 0,
                        "name": "Montenegro",
                        "longName": "Montenegro"
                    },
                    "eliminatedTeamId": null,
                    "statusId": 1,
                    "tournamentStage": "1",
                    "status": {
                        "utcTime": "2026-06-01T16:00:00.000Z",
                        "halfs": {
                            "firstHalfStarted": "01.06.2026 18:00:00"
                        },
                        "periodLength": 45,
                        "started": false,
                        "cancelled": false,
                        "finished": false
                    },
                    "timeTS": 1780329600000
                },
                {
                    "id": 5477263,
                    "leagueId": 914609,
                    "time": "01.06.2026 18:00",
                    "home": {
                        "id": 8497,
                        "score": 0,
                        "name": "Slovakia",
                        "longName": "Slovakia"
                    },
                    "away": {
                        "id": 8495,
                        "score": 0,
                        "name": "Malta",
                        "longName": "Malta"
                    },
                    "eliminatedTeamId": null,
                    "statusId": 1,
                    "tournamentStage": "1",
                    "status": {
                        "utcTime": "2026-06-01T16:00:00.000Z",
                        "halfs": {
                            "firstHalfStarted": "01.06.2026 18:00:00"
                        },
                        "periodLength": 45,
                        "started": false,
                        "cancelled": false,
                        "finished": false
                    },
                    "timeTS": 1780329600000
                },
                {
                    "id": 5269692,
                    "leagueId": 914609,
                    "time": "01.06.2026 19:00",
                    "home": {
                        "id": 8492,
                        "score": 0,
                        "name": "Norway",
                        "longName": "Norway"
                    },
                    "away": {
                        "id": 8520,
                        "score": 0,
                        "name": "Sweden",
                        "longName": "Sweden"
                    },
                    "eliminatedTeamId": null,
                    "statusId": 1,
                    "tournamentStage": "1",
                    "status": {
                        "utcTime": "2026-06-01T17:00:00.000Z",
                        "halfs": {
                            "firstHalfStarted": "01.06.2026 19:00:00"
                        },
                        "periodLength": 45,
                        "started": false,
                        "cancelled": false,
                        "finished": false
                    },
                    "timeTS": 1780333200000
                },
                {
                    "id": 5483930,
                    "leagueId": 914609,
                    "time": "01.06.2026 19:30",
                    "home": {
                        "id": 6595,
                        "score": 0,
                        "name": "Turkiye",
                        "longName": "Turkiye"
                    },
                    "away": {
                        "id": 8260,
                        "score": 0,
                        "name": "North Macedonia",
                        "longName": "North Macedonia"
                    },
                    "eliminatedTeamId": null,
                    "statusId": 1,
                    "tournamentStage": "1",
                    "status": {
                        "utcTime": "2026-06-01T17:30:00.000Z",
                        "halfs": {
                            "firstHalfStarted": "01.06.2026 19:30:00"
                        },
                        "periodLength": 45,
                        "started": false,
                        "cancelled": false,
                        "finished": false
                    },
                    "timeTS": 1780335000000
                },
                {
                    "id": 5154119,
                    "leagueId": 914609,
                    "time": "01.06.2026 20:45",
                    "home": {
                        "id": 8255,
                        "score": 0,
                        "name": "Austria",
                        "longName": "Austria"
                    },
                    "away": {
                        "id": 6719,
                        "score": 0,
                        "name": "Tunisia",
                        "longName": "Tunisia"
                    },
                    "eliminatedTeamId": null,
                    "statusId": 1,
                    "tournamentStage": "1",
                    "status": {
                        "utcTime": "2026-06-01T18:45:00.000Z",
                        "halfs": {
                            "firstHalfStarted": "01.06.2026 20:45:00"
                        },
                        "periodLength": 45,
                        "started": false,
                        "cancelled": false,
                        "finished": false
                    },
                    "timeTS": 1780339500000
                },
                {
                    "id": 5629008,
                    "leagueId": 914609,
                    "time": "02.06.2026 01:00",
                    "home": {
                        "id": 8258,
                        "score": 0,
                        "name": "Colombia",
                        "longName": "Colombia"
                    },
                    "away": {
                        "id": 6705,
                        "score": 0,
                        "name": "Costa Rica",
                        "longName": "Costa Rica"
                    },
                    "eliminatedTeamId": null,
                    "statusId": 1,
                    "tournamentStage": "1",
                    "status": {
                        "utcTime": "2026-06-01T23:00:00.000Z",
                        "halfs": {
                            "firstHalfStarted": "02.06.2026 01:00:00"
                        },
                        "periodLength": 45,
                        "started": false,
                        "cancelled": false,
                        "finished": false
                    },
                    "timeTS": 1780354800000
                },
                {
                    "id": 5142040,
                    "leagueId": 914609,
                    "time": "02.06.2026 03:00",
                    "home": {
                        "id": 5810,
                        "score": 0,
                        "name": "Canada",
                        "longName": "Canada"
                    },
                    "away": {
                        "id": 8700,
                        "score": 0,
                        "name": "Uzbekistan",
                        "longName": "Uzbekistan"
                    },
                    "eliminatedTeamId": null,
                    "statusId": 1,
                    "tournamentStage": "1",
                    "status": {
                        "utcTime": "2026-06-02T01:00:00.000Z",
                        "halfs": {
                            "firstHalfStarted": "02.06.2026 03:00:00"
                        },
                        "periodLength": 45,
                        "started": false,
                        "cancelled": false,
                        "finished": false
                    },
                    "timeTS": 1780362000000
                }
            ],
            "parentLeagueId": 114,
            "internalRank": 0,
            "liveRank": 999,
            "simpleLeague": false,
            "localRank": 60
        },
        {
            "ccode": "EGY",
            "id": 922249,
            "primaryId": 10270,
            "name": "League Cup",
            "matches": [
                {
                    "id": 5650002,
                    "leagueId": 922249,
                    "time": "01.06.2026 19:00",
                    "home": {
                        "id": 205190,
                        "score": 0,
                        "name": "Wadi Degla FC",
                        "longName": "Wadi Degla FC"
                    },
                    "away": {
                        "id": 101754,
                        "score": 0,
                        "name": "ENPPI",
                        "longName": "ENPPI"
                    },
                    "eliminatedTeamId": null,
                    "statusId": 1,
                    "tournamentStage": "1/2",
                    "status": {
                        "utcTime": "2026-06-01T17:00:00.000Z",
                        "halfs": {
                            "firstHalfStarted": "01.06.2026 19:00:00"
                        },
                        "periodLength": 45,
                        "started": false,
                        "cancelled": false,
                        "finished": false,
                        "aggregatedStr": "0 - 0"
                    },
                    "timeTS": 1780333200000
                }
            ],
            "parentLeagueId": 10270,
            "internalRank": 0,
            "liveRank": 999,
            "simpleLeague": false
        },
        {
            "ccode": "URU",
            "id": 930806,
            "primaryId": 161,
            "name": "Liga AUF Uruguaya Intermedio Grp. A",
            "matches": [
                {
                    "id": 5670398,
                    "leagueId": 930806,
                    "time": "01.06.2026 20:00",
                    "home": {
                        "id": 188313,
                        "score": 0,
                        "name": "Boston River",
                        "longName": "Boston River"
                    },
                    "away": {
                        "id": 2219,
                        "score": 0,
                        "name": "Liverpool FC",
                        "longName": "Liverpool FC"
                    },
                    "eliminatedTeamId": null,
                    "statusId": 1,
                    "tournamentStage": "3",
                    "status": {
                        "utcTime": "2026-06-01T18:00:00.000Z",
                        "halfs": {
                            "firstHalfStarted": "01.06.2026 20:00:00"
                        },
                        "periodLength": 45,
                        "started": false,
                        "cancelled": false,
                        "finished": false
                    },
                    "timeTS": 1780336800000
                },
                {
                    "id": 5670399,
                    "leagueId": 930806,
                    "time": "02.06.2026 01:00",
                    "home": {
                        "id": 8450,
                        "score": 0,
                        "name": "Pe\u00f1arol",
                        "longName": "Club Atletico Penarol"
                    },
                    "away": {
                        "id": 1834,
                        "score": 0,
                        "name": "Central Espanol",
                        "longName": "Central Espanol"
                    },
                    "eliminatedTeamId": null,
                    "statusId": 1,
                    "tournamentStage": "3",
                    "status": {
                        "utcTime": "2026-06-01T23:00:00.000Z",
                        "halfs": {
                            "firstHalfStarted": "02.06.2026 01:00:00"
                        },
                        "periodLength": 45,
                        "started": false,
                        "cancelled": false,
                        "finished": false
                    },
                    "timeTS": 1780354800000
                }
            ],
            "parentLeagueId": 161,
            "internalRank": 0,
            "liveRank": 999,
            "simpleLeague": false
        },
        {
            "ccode": "INT",
            "id": 928682,
            "primaryId": 305,
            "name": "Maurice Revello Tournament Grp. A",
            "matches": [
                {
                    "id": 5429858,
                    "leagueId": 928682,
                    "time": "02.06.2026 15:00",
                    "home": {
                        "id": 5947,
                        "score": 0,
                        "name": "China U20",
                        "longName": "China U20"
                    },
                    "away": {
                        "id": 439306,
                        "score": 0,
                        "name": "DR Congo U20",
                        "longName": "DR Congo U20"
                    },
                    "eliminatedTeamId": null,
                    "statusId": 1,
                    "tournamentStage": "2",
                    "status": {
                        "utcTime": "2026-06-02T13:00:00.000Z",
                        "halfs": {
                            "firstHalfStarted": "02.06.2026 15:00:00"
                        },
                        "periodLength": 45,
                        "started": false,
                        "cancelled": false,
                        "finished": false
                    },
                    "timeTS": 1780405200000
                }
            ],
            "parentLeagueId": 305,
            "internalRank": 0,
            "liveRank": 999,
            "simpleLeague": false
        },
        {
            "ccode": "INT",
            "id": 928683,
            "primaryId": 305,
            "name": "Maurice Revello Tournament Grp. B",
            "matches": [
                {
                    "id": 5429867,
                    "leagueId": 928683,
                    "time": "01.06.2026 18:30",
                    "home": {
                        "id": 169439,
                        "score": 0,
                        "name": "Venezuela U20",
                        "longName": "Venezuela U20"
                    },
                    "away": {
                        "id": 5869,
                        "score": 0,
                        "name": "Canada U20",
                        "longName": "Canada U20"
                    },
                    "eliminatedTeamId": null,
                    "statusId": 1,
                    "tournamentStage": "1",
                    "status": {
                        "utcTime": "2026-06-01T16:30:00.000Z",
                        "halfs": {
                            "firstHalfStarted": "01.06.2026 18:30:00"
                        },
                        "periodLength": 45,
                        "started": false,
                        "cancelled": false,
                        "finished": false
                    },
                    "timeTS": 1780331400000
                }
            ],
            "parentLeagueId": 305,
            "internalRank": 0,
            "liveRank": 999,
            "simpleLeague": false
        },
        {
            "ccode": "LUX",
            "id": 9174,
            "primaryId": 9174,
            "name": "National Division Qualification",
            "matches": [
                {
                    "id": 5671210,
                    "leagueId": 9174,
                    "time": "01.06.2026 19:30",
                    "home": {
                        "id": 187904,
                        "score": 0,
                        "name": "FC Jeunesse Canach",
                        "longName": "FC Jeunesse Canach"
                    },
                    "away": {
                        "id": 2001148,
                        "score": 0,
                        "name": "Walferdange",
                        "longName": "Walferdange"
                    },
                    "eliminatedTeamId": null,
                    "statusId": 1,
                    "tournamentStage": "final",
                    "status": {
                        "utcTime": "2026-06-01T17:30:00.000Z",
                        "halfs": {
                            "firstHalfStarted": "01.06.2026 19:30:00"
                        },
                        "periodLength": 45,
                        "started": false,
                        "cancelled": false,
                        "finished": false
                    },
                    "timeTS": 1780335000000
                }
            ],
            "internalRank": 0,
            "liveRank": 999,
            "simpleLeague": false
        },
        {
            "ccode": "GER",
            "id": 931416,
            "primaryId": 512,
            "name": "Regionalliga Promotion Playoff",
            "matches": [
                {
                    "id": 5629350,
                    "leagueId": 931416,
                    "time": "01.06.2026 18:30",
                    "home": {
                        "id": 145486,
                        "score": 0,
                        "name": "W\u00fcrzburger Kickers",
                        "longName": "W\u00fcrzburger Kickers"
                    },
                    "away": {
                        "id": 145597,
                        "score": 0,
                        "name": "Lokomotive Leipzig",
                        "longName": "Lokomotive Leipzig"
                    },
                    "eliminatedTeamId": null,
                    "statusId": 1,
                    "tournamentStage": "final",
                    "status": {
                        "utcTime": "2026-06-01T16:30:00.000Z",
                        "halfs": {
                            "firstHalfStarted": "01.06.2026 18:30:00"
                        },
                        "periodLength": 45,
                        "started": false,
                        "cancelled": false,
                        "finished": false,
                        "aggregatedStr": "1 - 0"
                    },
                    "timeTS": 1780331400000
                }
            ],
            "parentLeagueId": 512,
            "internalRank": 17,
            "liveRank": 999,
            "simpleLeague": false
        },
        {
            "ccode": "IRQ",
            "id": 905798,
            "primaryId": 524,
            "name": "Stars League",
            "matches": [
                {
                    "id": 5667307,
                    "leagueId": 905798,
                    "time": "01.06.2026 17:00",
                    "home": {
                        "id": 101661,
                        "score": 0,
                        "name": "Al Naft",
                        "longName": "Al Naft"
                    },
                    "away": {
                        "id": 1298364,
                        "score": 0,
                        "name": "Newroz",
                        "longName": "Newroz"
                    },
                    "eliminatedTeamId": null,
                    "statusId": 1,
                    "tournamentStage": "38",
                    "status": {
                        "utcTime": "2026-06-01T15:00:00.000Z",
                        "halfs": {
                            "firstHalfStarted": "01.06.2026 17:00:00"
                        },
                        "periodLength": 45,
                        "started": false,
                        "cancelled": false,
                        "finished": false
                    },
                    "timeTS": 1780326000000
                },
                {
                    "id": 5667306,
                    "leagueId": 905798,
                    "time": "01.06.2026 17:00",
                    "home": {
                        "id": 1811191,
                        "score": 0,
                        "name": "Al-Mosul",
                        "longName": "Al-Mosul"
                    },
                    "away": {
                        "id": 1087313,
                        "score": 0,
                        "name": "Al-Qasim",
                        "longName": "Al-Qasim"
                    },
                    "eliminatedTeamId": null,
                    "statusId": 1,
                    "tournamentStage": "38",
                    "status": {
                        "utcTime": "2026-06-01T15:00:00.000Z",
                        "halfs": {
                            "firstHalfStarted": "01.06.2026 17:00:00"
                        },
                        "periodLength": 45,
                        "started": false,
                        "cancelled": false,
                        "finished": false
                    },
                    "timeTS": 1780326000000
                },
                {
                    "id": 5667308,
                    "leagueId": 905798,
                    "time": "01.06.2026 17:00",
                    "home": {
                        "id": 165214,
                        "score": 0,
                        "name": "Diyala",
                        "longName": "Diyala"
                    },
                    "away": {
                        "id": 101650,
                        "score": 0,
                        "name": "Duhok",
                        "longName": "Duhok"
                    },
                    "eliminatedTeamId": null,
                    "statusId": 1,
                    "tournamentStage": "38",
                    "status": {
                        "utcTime": "2026-06-01T15:00:00.000Z",
                        "halfs": {
                            "firstHalfStarted": "01.06.2026 17:00:00"
                        },
                        "periodLength": 45,
                        "started": false,
                        "cancelled": false,
                        "finished": false
                    },
                    "timeTS": 1780326000000
                },
                {
                    "id": 5667309,
                    "leagueId": 905798,
                    "time": "01.06.2026 19:30",
                    "home": {
                        "id": 101643,
                        "score": 0,
                        "name": "Al Najaf",
                        "longName": "Al Najaf"
                    },
                    "away": {
                        "id": 101659,
                        "score": 0,
                        "name": "Al Zawraa",
                        "longName": "Al Zawraa"
                    },
                    "eliminatedTeamId": null,
                    "statusId": 1,
                    "tournamentStage": "38",
                    "status": {
                        "utcTime": "2026-06-01T17:30:00.000Z",
                        "halfs": {
                            "firstHalfStarted": "01.06.2026 19:30:00"
                        },
                        "periodLength": 45,
                        "started": false,
                        "cancelled": false,
                        "finished": false
                    },
                    "timeTS": 1780335000000
                },
                {
                    "id": 5667310,
                    "leagueId": 905798,
                    "time": "01.06.2026 19:30",
                    "home": {
                        "id": 101660,
                        "score": 0,
                        "name": "Al Talaba",
                        "longName": "Al Talaba"
                    },
                    "away": {
                        "id": 191818,
                        "score": 0,
                        "name": "Al Karkh",
                        "longName": "Al Karkh"
                    },
                    "eliminatedTeamId": null,
                    "statusId": 1,
                    "tournamentStage": "38",
                    "status": {
                        "utcTime": "2026-06-01T17:30:00.000Z",
                        "halfs": {
                            "firstHalfStarted": "01.06.2026 19:30:00"
                        },
                        "periodLength": 45,
                        "started": false,
                        "cancelled": false,
                        "finished": false
                    },
                    "timeTS": 1780335000000
                }
            ],
            "parentLeagueId": 524,
            "internalRank": 0,
            "liveRank": 999,
            "simpleLeague": false
        },
        {
            "ccode": "ROU",
            "id": 9587,
            "primaryId": 9587,
            "name": "Superliga Qualification",
            "matches": [
                {
                    "id": 5651882,
                    "leagueId": 9587,
                    "time": "01.06.2026 19:30",
                    "home": {
                        "id": 405332,
                        "score": 0,
                        "name": "FC Voluntari",
                        "longName": "FC Voluntari"
                    },
                    "away": {
                        "id": 864269,
                        "score": 0,
                        "name": "Hermannstadt",
                        "longName": "Hermannstadt"
                    },
                    "eliminatedTeamId": null,
                    "statusId": 1,
                    "tournamentStage": "final",
                    "status": {
                        "utcTime": "2026-06-01T17:30:00.000Z",
                        "halfs": {
                            "firstHalfStarted": "01.06.2026 19:30:00"
                        },
                        "periodLength": 45,
                        "started": false,
                        "cancelled": false,
                        "finished": false,
                        "aggregatedStr": "2 - 3"
                    },
                    "timeTS": 1780335000000
                }
            ],
            "internalRank": 6,
            "liveRank": 999,
            "simpleLeague": false
        },
        {
            "ccode": "ARG",
            "id": 916561,
            "primaryId": 9213,
            "name": "Primera B Metropolitana",
            "matches": [
                {
                    "id": 5113859,
                    "leagueId": 916561,
                    "time": "01.06.2026 20:30",
                    "home": {
                        "id": 581807,
                        "score": 0,
                        "name": "Argentino de Quilmes",
                        "longName": "Argentino de Quilmes"
                    },
                    "away": {
                        "id": 581820,
                        "score": 0,
                        "name": "Ituzaingo",
                        "longName": "Ituzaingo"
                    },
                    "eliminatedTeamId": null,
                    "statusId": 1,
                    "tournamentStage": "18",
                    "status": {
                        "utcTime": "2026-06-01T18:30:00.000Z",
                        "halfs": {
                            "firstHalfStarted": "01.06.2026 20:30:00"
                        },
                        "periodLength": 45,
                        "started": false,
                        "cancelled": false,
                        "finished": false
                    },
                    "timeTS": 1780338600000
                }
            ],
            "parentLeagueId": 9213,
            "internalRank": 7,
            "liveRank": 3,
            "simpleLeague": false
        },
        {
            "ccode": "BRA",
            "id": 9429,
            "primaryId": 9429,
            "name": "Copa do Nordeste",
            "matches": [
                {
                    "id": 1000012573,
                    "leagueId": 9429,
                    "time": "02.06.2026 02:00",
                    "home": {
                        "id": 8287,
                        "score": 0,
                        "name": "Fortaleza",
                        "longName": "Fortaleza"
                    },
                    "away": {
                        "id": 7733,
                        "score": 0,
                        "name": "Vitoria",
                        "longName": "Vitoria"
                    },
                    "eliminatedTeamId": null,
                    "statusId": 1,
                    "tournamentStage": "Final",
                    "status": {
                        "utcTime": "2026-06-02T00:00:00.000Z",
                        "halfs": {
                            "firstHalfStarted": "02.06.2026 02:00:00"
                        },
                        "periodLength": 45,
                        "started": false,
                        "cancelled": false,
                        "finished": false
                    },
                    "timeTS": 1780358400000
                }
            ],
            "internalRank": 0,
            "liveRank": 0,
            "simpleLeague": false
        },
        {
            "ccode": "CHI",
            "id": 9126,
            "primaryId": 9126,
            "name": "Primera B",
            "matches": [
                {
                    "id": 1000007220,
                    "leagueId": 9126,
                    "time": "02.06.2026 01:00",
                    "home": {
                        "id": 162905,
                        "score": 0,
                        "name": "Curico Unido",
                        "longName": "Curico Unido"
                    },
                    "away": {
                        "id": 6201,
                        "score": 0,
                        "name": "Antofagasta",
                        "longName": "Antofagasta"
                    },
                    "eliminatedTeamId": null,
                    "statusId": 1,
                    "tournamentStage": "14",
                    "status": {
                        "utcTime": "2026-06-01T23:00:00.000Z",
                        "halfs": {
                            "firstHalfStarted": "02.06.2026 01:00:00"
                        },
                        "periodLength": 45,
                        "started": false,
                        "cancelled": false,
                        "finished": false
                    },
                    "timeTS": 1780354800000
                },
                {
                    "id": 1000007221,
                    "leagueId": 9126,
                    "time": "02.06.2026 01:00",
                    "home": {
                        "id": 584834,
                        "score": 0,
                        "name": "Deportes Santa Cruz",
                        "longName": "Deportes Santa Cruz"
                    },
                    "away": {
                        "id": 192436,
                        "score": 0,
                        "name": "Deportes Copiapo",
                        "longName": "Deportes Copiapo"
                    },
                    "eliminatedTeamId": null,
                    "statusId": 1,
                    "tournamentStage": "14",
                    "status": {
                        "utcTime": "2026-06-01T23:00:00.000Z",
                        "halfs": {
                            "firstHalfStarted": "02.06.2026 01:00:00"
                        },
                        "periodLength": 45,
                        "started": false,
                        "cancelled": false,
                        "finished": false
                    },
                    "timeTS": 1780354800000
                }
            ],
            "internalRank": 0,
            "liveRank": 0,
            "simpleLeague": false
        },
        {
            "ccode": "BOL",
            "id": 144,
            "primaryId": 144,
            "name": "Primera Divisi\u00f3n",
            "matches": [
                {
                    "id": 1000010887,
                    "leagueId": 144,
                    "time": "02.06.2026 02:00",
                    "home": {
                        "id": 879029,
                        "score": 0,
                        "name": "Universitario de Vinto",
                        "longName": "Universitario de Vinto"
                    },
                    "away": {
                        "id": 49720,
                        "score": 0,
                        "name": "Aurora",
                        "longName": "Aurora"
                    },
                    "eliminatedTeamId": null,
                    "statusId": 1,
                    "tournamentStage": "10",
                    "status": {
                        "utcTime": "2026-06-02T00:00:00.000Z",
                        "halfs": {
                            "firstHalfStarted": "02.06.2026 02:00:00"
                        },
                        "periodLength": 45,
                        "started": false,
                        "cancelled": false,
                        "finished": false
                    },
                    "timeTS": 1780358400000
                }
            ],
            "internalRank": 0,
            "liveRank": 0,
            "simpleLeague": false
        },
        {
            "ccode": "ECU",
            "id": 246,
            "primaryId": 246,
            "name": "Serie A",
            "matches": [
                {
                    "id": 1000008997,
                    "leagueId": 246,
                    "time": "02.06.2026 00:00",
                    "home": {
                        "id": 1370528,
                        "score": 0,
                        "name": "Leones del Norte",
                        "longName": "Leones del Norte"
                    },
                    "away": {
                        "id": 6609,
                        "score": 0,
                        "name": "CSD Macara",
                        "longName": "CSD Macara"
                    },
                    "eliminatedTeamId": null,
                    "statusId": 1,
                    "tournamentStage": "16",
                    "status": {
                        "utcTime": "2026-06-01T22:00:00.000Z",
                        "halfs": {
                            "firstHalfStarted": "02.06.2026 00:00:00"
                        },
                        "periodLength": 45,
                        "started": false,
                        "cancelled": false,
                        "finished": false
                    },
                    "timeTS": 1780351200000
                },
                {
                    "id": 1000008993,
                    "leagueId": 246,
                    "time": "02.06.2026 02:30",
                    "home": {
                        "id": 113054,
                        "score": 0,
                        "name": "Tecnico Universitario",
                        "longName": "Tecnico Universitario"
                    },
                    "away": {
                        "id": 6453,
                        "score": 0,
                        "name": "Barcelona SC",
                        "longName": "Barcelona SC"
                    },
                    "eliminatedTeamId": null,
                    "statusId": 1,
                    "tournamentStage": "16",
                    "status": {
                        "utcTime": "2026-06-02T00:30:00.000Z",
                        "halfs": {
                            "firstHalfStarted": "02.06.2026 02:30:00"
                        },
                        "periodLength": 45,
                        "started": false,
                        "cancelled": false,
                        "finished": false
                    },
                    "timeTS": 1780360200000
                }
            ],
            "internalRank": 0,
            "liveRank": 0,
            "simpleLeague": false
        },
        {
            "ccode": "BRA",
            "id": 8814,
            "primaryId": 8814,
            "name": "Serie B",
            "matches": [
                {
                    "id": 5190539,
                    "leagueId": 8814,
                    "time": "02.06.2026 00:00",
                    "home": {
                        "id": 8630,
                        "score": 0,
                        "name": "Ponte Preta",
                        "longName": "Ponte Preta"
                    },
                    "away": {
                        "id": 8355,
                        "score": 0,
                        "name": "Botafogo SP",
                        "longName": "Botafogo SP"
                    },
                    "eliminatedTeamId": null,
                    "statusId": 1,
                    "tournamentStage": "11",
                    "status": {
                        "utcTime": "2026-06-01T22:00:00.000Z",
                        "halfs": {
                            "firstHalfStarted": "02.06.2026 00:00:00"
                        },
                        "periodLength": 45,
                        "started": false,
                        "cancelled": false,
                        "finished": false
                    },
                    "timeTS": 1780351200000
                }
            ],
            "internalRank": 0,
            "liveRank": 0,
            "simpleLeague": false
        },
        {
            "ccode": "BRA",
            "id": 8971,
            "primaryId": 8971,
            "name": "Serie C",
            "matches": [
                {
                    "id": 1000009428,
                    "leagueId": 8971,
                    "time": "02.06.2026 01:00",
                    "home": {
                        "id": 1320333,
                        "score": 0,
                        "name": "Barra FC",
                        "longName": "Barra FC"
                    },
                    "away": {
                        "id": 197692,
                        "score": 0,
                        "name": "Brusque",
                        "longName": "Brusque"
                    },
                    "eliminatedTeamId": null,
                    "statusId": 1,
                    "tournamentStage": "9",
                    "status": {
                        "utcTime": "2026-06-01T23:00:00.000Z",
                        "halfs": {
                            "firstHalfStarted": "02.06.2026 01:00:00"
                        },
                        "periodLength": 45,
                        "started": false,
                        "cancelled": false,
                        "finished": false
                    },
                    "timeTS": 1780354800000
                }
            ],
            "internalRank": 0,
            "liveRank": 0,
            "simpleLeague": false
        },
        {
            "ccode": "BRA",
            "id": 9464,
            "primaryId": 9464,
            "name": "Serie D",
            "matches": [
                {
                    "id": 1000010754,
                    "leagueId": 9464,
                    "time": "02.06.2026 00:00",
                    "home": {
                        "id": 1696139,
                        "score": 0,
                        "name": "Tirol",
                        "longName": "Tirol"
                    },
                    "away": {
                        "id": 197695,
                        "score": 0,
                        "name": "Ferroviario",
                        "longName": "Ferroviario"
                    },
                    "eliminatedTeamId": null,
                    "statusId": 1,
                    "tournamentStage": "9",
                    "status": {
                        "utcTime": "2026-06-01T22:00:00.000Z",
                        "halfs": {
                            "firstHalfStarted": "02.06.2026 00:00:00"
                        },
                        "periodLength": 45,
                        "started": false,
                        "cancelled": false,
                        "finished": false
                    },
                    "timeTS": 1780351200000
                },
                {
                    "id": 1000010782,
                    "leagueId": 9464,
                    "time": "02.06.2026 01:15",
                    "home": {
                        "id": 162172,
                        "score": 0,
                        "name": "Marcilio Dias",
                        "longName": "Marcilio Dias"
                    },
                    "away": {
                        "id": 1223346,
                        "score": 0,
                        "name": "Azuriz",
                        "longName": "Azuriz"
                    },
                    "eliminatedTeamId": null,
                    "statusId": 1,
                    "tournamentStage": "9",
                    "status": {
                        "utcTime": "2026-06-01T23:15:00.000Z",
                        "halfs": {
                            "firstHalfStarted": "02.06.2026 01:15:00"
                        },
                        "periodLength": 45,
                        "started": false,
                        "cancelled": false,
                        "finished": false
                    },
                    "timeTS": 1780355700000
                }
            ],
            "internalRank": 0,
            "liveRank": 0,
            "simpleLeague": false
        }
    ],
    "date": "20260602"
}